[
  {
    "ET0_hor":15.935,
    "ET0_west":15.403,
    "ET0_south":23.097,
    "ET0_north":12.372,
    "ET0_east":14.006
  },
  {
    "ET0_hor":20.665,
    "ET0_west":16.801,
    "ET0_south":27.961,
    "ET0_north":12.517,
    "ET0_east":16.837
  },
  {
    "ET0_hor":41.823,
    "ET0_west":32.411,
    "ET0_south":46.024,
    "ET0_north":21.046,
    "ET0_east":31.574
  },
  {
    "ET0_hor":71.567,
    "ET0_west":51.348,
    "ET0_south":59.387,
    "ET0_north":29.685,
    "ET0_east":51.19
  },
  {
    "ET0_hor":104.272,
    "ET0_west":72.829,
    "ET0_south":68.196,
    "ET0_north":46.354,
    "ET0_east":72.418
  },
  {
    "ET0_hor":114.99,
    "ET0_west":78.581,
    "ET0_south":68.257,
    "ET0_north":53.996,
    "ET0_east":77.824
  },
  {
    "ET0_hor":115.623,
    "ET0_west":77.371,
    "ET0_south":70.579,
    "ET0_north":49.888,
    "ET0_east":77.432
  },
  {
    "ET0_hor":101.546,
    "ET0_west":72.18,
    "ET0_south":75.086,
    "ET0_north":38.342,
    "ET0_east":67.132
  },
  {
    "ET0_hor":59.12,
    "ET0_west":41.558,
    "ET0_south":57.102,
    "ET0_north":21.207,
    "ET0_east":41.717
  },
  {
    "ET0_hor":31.525,
    "ET0_west":26.543,
    "ET0_south":43.537,
    "ET0_north":12.242,
    "ET0_east":21.595
  },
  {
    "ET0_hor":15.776,
    "ET0_west":14.525,
    "ET0_south":24.083,
    "ET0_north":9.71,
    "ET0_east":12.333
  },
  {
    "ET0_hor":12.413,
    "ET0_west":11.222,
    "ET0_south":17.756,
    "ET0_north":9.59,
    "ET0_east":10.86
  }
]